GoYuyanGaoxingnengBiancheng/README.md
GoYuyanGaoxingnengBiancheng/__init__.py
GoYuyanGaoxingnengBiancheng/__main__.py
GoYuyanGaoxingnengBiancheng/file.epub
GoYuyanGaoxingnengBiancheng/index.html
GoYuyanGaoxingnengBiancheng/css/__init__.py
GoYuyanGaoxingnengBiancheng/css/annotations.css
GoYuyanGaoxingnengBiancheng/css/main.css
GoYuyanGaoxingnengBiancheng/css/normalize.css
GoYuyanGaoxingnengBiancheng/css/popup.css
GoYuyanGaoxingnengBiancheng/font/__init__.py
GoYuyanGaoxingnengBiancheng/font/fontello.eot
GoYuyanGaoxingnengBiancheng/font/fontello.svg
GoYuyanGaoxingnengBiancheng/font/fontello.ttf
GoYuyanGaoxingnengBiancheng/font/fontello.woff
GoYuyanGaoxingnengBiancheng/img/__init__.py
GoYuyanGaoxingnengBiancheng/img/annotator-glyph-sprite.png
GoYuyanGaoxingnengBiancheng/img/annotator-icon-sprite.png
GoYuyanGaoxingnengBiancheng/img/apple-touch-icon.png
GoYuyanGaoxingnengBiancheng/img/cancelfullscreen.png
GoYuyanGaoxingnengBiancheng/img/close.png
GoYuyanGaoxingnengBiancheng/img/fullscreen.png
GoYuyanGaoxingnengBiancheng/img/loader.gif
GoYuyanGaoxingnengBiancheng/img/menu-icon.png
GoYuyanGaoxingnengBiancheng/img/save.png
GoYuyanGaoxingnengBiancheng/img/saved.png
GoYuyanGaoxingnengBiancheng/img/settings-s.png
GoYuyanGaoxingnengBiancheng/img/settings.png
GoYuyanGaoxingnengBiancheng/img/star.png
GoYuyanGaoxingnengBiancheng/js/__init__.py
GoYuyanGaoxingnengBiancheng/js/epub.js
GoYuyanGaoxingnengBiancheng/js/epub.min.js
GoYuyanGaoxingnengBiancheng/js/epub.min.map
GoYuyanGaoxingnengBiancheng/js/hooks.min.js
GoYuyanGaoxingnengBiancheng/js/hooks.min.map
GoYuyanGaoxingnengBiancheng/js/reader.js
GoYuyanGaoxingnengBiancheng/js/reader.js.map
GoYuyanGaoxingnengBiancheng/js/reader.min.js
GoYuyanGaoxingnengBiancheng/js/reader.min.map
GoYuyanGaoxingnengBiancheng/js/hooks/__init__.py
GoYuyanGaoxingnengBiancheng/js/hooks/extensions/__init__.py
GoYuyanGaoxingnengBiancheng/js/hooks/extensions/highlight.js
GoYuyanGaoxingnengBiancheng/js/libs/__init__.py
go_yuyan_gaoxingneng_biancheng-2024.3.5.0.dist-info/METADATA
go_yuyan_gaoxingneng_biancheng-2024.3.5.0.dist-info/WHEEL
go_yuyan_gaoxingneng_biancheng-2024.3.5.0.dist-info/entry_points.txt
go_yuyan_gaoxingneng_biancheng-2024.3.5.0.dist-info/top_level.txt
go_yuyan_gaoxingneng_biancheng-2024.3.5.0.dist-info/RECORD
